grin/__init__.py
grin/colors.py
grin/datablock.py
grin/grin.py
grin/grind.py
grin/main.py
grin/options.py
grin/recognizer.py
grin/utils.py
grin3-2.6.1.dist-info/LICENSE.txt
grin3-2.6.1.dist-info/METADATA
grin3-2.6.1.dist-info/WHEEL
grin3-2.6.1.dist-info/entry_points.txt
grin3-2.6.1.dist-info/top_level.txt
grin3-2.6.1.dist-info/RECORD
