Metadata-Version: 2.1
Name: grin3
Version: 2.6.1
Summary: A grep program configured the way I like it. (python3 port)
Home-page: https://pypi.org/project/grin3/
Author: Robert Kern
Author-email: robert.kern@enthought.com
Maintainer: Raffaele Salmaso
Maintainer-email: raffaele@salmaso.org
Project-URL: Github, https://github.com/rsalmaso/grin3
Project-URL: Gitlab, https://gitlab.com/rsalmaso/grin3
Classifier: License :: OSI Approved :: BSD License
Classifier: Development Status :: 5 - Production/Stable
Classifier: Environment :: Console
Classifier: Intended Audience :: Developers
Classifier: Operating System :: OS Independent
Classifier: Programming Language :: Python
Classifier: Programming Language :: Python :: 3
Classifier: Programming Language :: Python :: 3.5
Classifier: Programming Language :: Python :: 3.6
Classifier: Programming Language :: Python :: 3.7
Classifier: Programming Language :: Python :: 3.8
Classifier: Programming Language :: Python :: 3.9
Classifier: Programming Language :: Python :: 3.10
Classifier: Programming Language :: Python :: 3.11
Classifier: Programming Language :: Python :: Implementation :: CPython
Classifier: Programming Language :: Python :: Implementation :: PyPy
Classifier: Topic :: Utilities
Requires-Python: >=3.5
License-File: LICENSE.txt
